trend/__init__.py
trend-0.1.dist-info/DESCRIPTION.rst
trend-0.1.dist-info/METADATA
trend-0.1.dist-info/RECORD
trend-0.1.dist-info/WHEEL
trend-0.1.dist-info/metadata.json
trend-0.1.dist-info/top_level.txt
