Metadata-Version: 2.0
Name: trend
Version: 0.1
Summary: Algorithms for detecting trends in time-series data.
Home-page: https://github.com/USGS-python/trend
Author: Timothy Hodson
Author-email: thodson@usgs.gov
License: MIT
Platform: UNKNOWN
